<annotation>
	<folder>cups-detection</folder>
	<filename>23-img06.png</filename>
	<path>/mnt/files/Datasets/images/cups-detection/23-img06.png</path>
	<source>
		<database>Unknown</database>
	</source>
	<size>
		<width>640</width>
		<height>350</height>
		<depth>3</depth>
	</size>
	<segmented>0</segmented>
	<object>
		<name>hole</name>
		<pose>Unspecified</pose>
		<truncated>0</truncated>
		<difficult>0</difficult>
		<bndbox>
			<xmin>430</xmin>
			<ymin>102</ymin>
			<xmax>496</xmax>
			<ymax>182</ymax>
		</bndbox>
	</object>
</annotation>
